aptosetl/__init__.py
aptosetl/api/__init__.py
aptosetl/api/aptos_node.py
aptosetl/cli/__init__.py
aptosetl/cli/export_blocks_and_transactions.py
aptosetl/domain/__init__.py
aptosetl/domain/block.py
aptosetl/domain/transaction.py
aptosetl/jobs/__init__.py
aptosetl/jobs/export_blocks_job.py
aptosetl/jobs/exporters/__init__.py
aptosetl/jobs/exporters/blocks_and_transactions_item_exporter.py
aptosetl/streaming/__init__.py
aptosetl/streaming/aptos_item_id_calculator.py
aptosetl/streaming/aptos_streamer_adapter.py
bitcoinetl/__init__.py
bitcoinetl/__main__.py
bitcoinetl/btc_utils.py
bitcoinetl/json_rpc_requests.py
bitcoinetl/cli/__init__.py
bitcoinetl/cli/enrich_transactions.py
bitcoinetl/cli/export_all.py
bitcoinetl/cli/export_blocks_and_transactions.py
bitcoinetl/cli/filter_items.py
bitcoinetl/cli/get_block_range_for_date.py
bitcoinetl/cli/stream.py
bitcoinetl/domain/__init__.py
bitcoinetl/domain/block.py
bitcoinetl/domain/join_split.py
bitcoinetl/domain/transaction.py
bitcoinetl/domain/transaction_input.py
bitcoinetl/domain/transaction_output.py
bitcoinetl/enumeration/__init__.py
bitcoinetl/enumeration/chain.py
bitcoinetl/jobs/__init__.py
bitcoinetl/jobs/enrich_transactions.py
bitcoinetl/jobs/export_all.py
bitcoinetl/jobs/export_blocks_job.py
bitcoinetl/jobs/exporters/__init__.py
bitcoinetl/jobs/exporters/blocks_and_transactions_item_exporter.py
bitcoinetl/mappers/__init__.py
bitcoinetl/mappers/block_mapper.py
bitcoinetl/mappers/join_split_mapper.py
bitcoinetl/mappers/transaction_input_mapper.py
bitcoinetl/mappers/transaction_mapper.py
bitcoinetl/mappers/transaction_output_mapper.py
bitcoinetl/rpc/__init__.py
bitcoinetl/rpc/bitcoin_rpc.py
bitcoinetl/rpc/request.py
bitcoinetl/service/__init__.py
bitcoinetl/service/btc_block_range_service.py
bitcoinetl/service/btc_block_timestamp_graph.py
bitcoinetl/service/btc_script_service.py
bitcoinetl/service/btc_service.py
bitcoinetl/service/genesis_transactions.py
bitcoinetl/streaming/__init__.py
ortegeetl-2.0.3.dist-info/LICENSE
ortegeetl-2.0.3.dist-info/METADATA
ortegeetl-2.0.3.dist-info/WHEEL
ortegeetl-2.0.3.dist-info/entry_points.txt
ortegeetl-2.0.3.dist-info/top_level.txt
ortegeetl-2.0.3.dist-info/RECORD
