Metadata-Version: 2.1
Name: ortegeetl
Version: 2.0.3
Summary: Tools for exporting Blockchain data to CSV or JSON
Home-page: https://github.com/Ortege-xyz/ortegeETL
Author: Ortege
Author-email: 
Project-URL: Bug Reports, https://github.com/Ortege-xyz/ortegeETL/issues
Project-URL: Source, https://github.com/Ortege-xyz/ortegeETL
Keywords: blockchain
Classifier: Development Status :: 5 - Production/Stable
Classifier: Intended Audience :: Developers
Classifier: License :: OSI Approved :: MIT License
Classifier: Programming Language :: Python :: 3
Classifier: Programming Language :: Python :: 3.7
Classifier: Programming Language :: Python :: 3.8
Classifier: Programming Language :: Python :: 3.9
Requires-Python: >=3.7.2,<4
License-File: LICENSE
Requires-Dist: web3<6,>=5.29
Requires-Dist: eth-utils==1.10
Requires-Dist: eth-abi<3.0.0,>=2.2.0
Requires-Dist: python-dateutil<3,>=2.8.0
Requires-Dist: click<9,>=8.0.4
Requires-Dist: ethereum-dasm==0.1.4
Requires-Dist: urllib3<2
Requires-Dist: base58
Requires-Dist: requests
Requires-Dist: stellar-sdk==9.2.0
Provides-Extra: streaming
Requires-Dist: timeout-decorator==0.4.1; extra == "streaming"
Requires-Dist: google-cloud-pubsub==2.13.0; extra == "streaming"
Requires-Dist: google-cloud-storage==1.33.0; extra == "streaming"
Requires-Dist: kafka-python==2.0.2; extra == "streaming"
Requires-Dist: sqlalchemy==1.4; extra == "streaming"
Requires-Dist: pg8000==1.16.6; extra == "streaming"
Requires-Dist: libcst==0.3.21; extra == "streaming"
Requires-Dist: grpcio==1.46.3; extra == "streaming"
Provides-Extra: streaming-kinesis
Requires-Dist: boto3==1.24.11; extra == "streaming-kinesis"
Requires-Dist: botocore==1.27.11; extra == "streaming-kinesis"
Provides-Extra: dev
Requires-Dist: pytest~=4.3.0; extra == "dev"
